[{"id": "0EWBQEZCHQPK9VKKF3XNAHPD7J", "value": "0.00", "feed_id": 1738539, "created_at": "2021-11-13T06:03:28.389Z"}, {"id": "0EWBSPG71879MN5R00BM9VTCP2", "value": "2086.63", "feed_id": 1738539, "created_at": "2021-11-13T08:08:28.420Z"}, {"id": "0EWBWYH7A8R9K3Y1JDCJ9FG6MY", "value": "0.00", "feed_id": 1738539, "created_at": "2021-11-13T11:10:16.915Z"}, {"id": "0EWBZZ6AQZ4YH7DE9JK8G63GDC", "value": "0.00", "feed_id": 1738539, "created_at": "2021-11-13T13:59:12.409Z"}, {"id": "0EWC3BYYHDGP316WYVNTTZW87A", "value": "0.00", "feed_id": 1738539, "created_at": "2021-11-13T17:09:17.700Z"}, {"id": "0EWC757H4FDPVR25KPZK1M6H6B", "value": "0.00", "feed_id": 1738539, "created_at": "2021-11-13T20:41:13.588Z"}, {"id": "0EWCA1XMY3A11ECBV49HYJ575B", "value": "0.00", "feed_id": 1738539, "created_at": "2021-11-13T23:23:12.966Z"}, {"id": "0EWCCVSG8J5362W6QVZFJ535HZ", "value": "0.00", "feed_id": 1738539, "created_at": "2021-11-14T02:00:16.565Z"}, {"id": "0EWCFS0X7MD3SYZ04P59MPPT6K", "value": "0.00", "feed_id": 1738539, "created_at": "2021-11-14T04:43:12.587Z"}, {"id": "0EWCJJ9CQCFNT0DYY5ZS0AN8AS", "value": "0.00", "feed_id": 1738539, "created_at": "2021-11-14T07:19:12.714Z"}, {"id": "0EWCNQJCAB2XTKDD7WYRR82R68", "value": "0.00", "feed_id": 1738539, "created_at": "2021-11-14T10:16:12.781Z"}, {"id": "0EWCRY09SG0EPZG7MNTJ7EJJH0", "value": "0.00", "feed_id": 1738539, "created_at": "2021-11-14T13:15:13.873Z"}, {"id": "0EWCWBAD420B42BFV5J6WRQ3D0", "value": "2086.63", "feed_id": 1738539, "created_at": "2021-11-14T16:26:16.460Z"}, {"id": "0EWCZC0VGVT0RPVSHD3KA7TS8Q", "value": "2086.63", "feed_id": 1738539, "created_at": "2021-11-14T19:15:16.354Z"}, {"id": "0EWD245NFYVMPGFGSSEWSRW59C", "value": "2086.63", "feed_id": 1738539, "created_at": "2021-11-14T21:49:19.590Z"}, {"id": "0EWD57KBVF8YK988EFM0986D27", "value": "2086.63", "feed_id": 1738539, "created_at": "2021-11-15T00:43:05.380Z"}, {"id": "0EWD86P6JXKZM7WKCVE2PYS6F7", "value": "2086.63", "feed_id": 1738539, "created_at": "2021-11-15T03:29:16.143Z"}, {"id": "0EWDB5CWF5156NQ92PYJ76EBRH", "value": "2086.63", "feed_id": 1738539, "created_at": "2021-11-15T06:14:47.088Z"}, {"id": "0EWDE37SFQ0HNWY3Q1AP3QF125", "value": "2086.63", "feed_id": 1738539, "created_at": "2021-11-15T08:58:47.013Z"}, {"id": "0EWDH52ZCSZ3KNA6636JY58BKG", "value": "2086.63", "feed_id": 1738539, "created_at": "2021-11-15T11:49:47.279Z"}, {"id": "0EWDM1XDCWK722Z6YEAAEN1YW0", "value": "2086.63", "feed_id": 1738539, "created_at": "2021-11-15T14:32:00.809Z"}, {"id": "0EWDPNFK36A66S3ASRATVSKAGX", "value": "2086.63", "feed_id": 1738539, "created_at": "2021-11-15T16:58:03.555Z"}, {"id": "0EWDS6PZCMDCCAYC6ZJ8SDJDXK", "value": "2086.63", "feed_id": 1738539, "created_at": "2021-11-15T19:20:01.217Z"}, {"id": "0EWDVJ7DHY7SZFPK5ZX0AQJN29", "value": "2086.63", "feed_id": 1738539, "created_at": "2021-11-15T21:31:59.417Z"}, {"id": "0EWE75SGG2WWKH3SWJRPT4E2GW", "value": "2086.63", "feed_id": 1738539, "created_at": "2021-11-16T08:21:20.870Z"}, {"id": "0EWE92RYGYGK8V0XVJMSK82AAE", "value": "2086.63", "feed_id": 1738539, "created_at": "2021-11-16T10:07:55.343Z"}, {"id": "0EWEBHK4Z5X5GSGW2026BY6VRF", "value": "2086.63", "feed_id": 1738539, "created_at": "2021-11-16T12:25:40.093Z"}, {"id": "0EWEDJ37PW7Q95E2RRAG2THDNF", "value": "2086.63", "feed_id": 1738539, "created_at": "2021-11-16T14:18:23.689Z"}, {"id": "0EWEFGDA135CBEAFXZ4NJ5J6P1", "value": "2086.63", "feed_id": 1738539, "created_at": "2021-11-16T16:07:17.865Z"}, {"id": "0EWEHB5K7AA5C2FMARSX04WPDJ", "value": "2086.63", "feed_id": 1738539, "created_at": "2021-11-16T17:49:59.191Z"}, {"id": "0EWEK5JRXD8V81MPYKEWJ5GH03", "value": "2086.63", "feed_id": 1738539, "created_at": "2021-11-16T19:32:04.113Z"}, {"id": "0EWEN0A1T1ATW8CHDRXQX8Y34B", "value": "2086.63", "feed_id": 1738539, "created_at": "2021-11-16T21:14:42.131Z"}, {"id": "0EWEPTXSZJC6A2GD3RR1T5N7XF", "value": "2086.63", "feed_id": 1738539, "created_at": "2021-11-16T22:57:08.606Z"}, {"id": "0EWERNW3297NYZ887SYJ62CMRY", "value": "2086.63", "feed_id": 1738539, "created_at": "2021-11-17T00:40:09.581Z"}, {"id": "0EWETH4Z12AKVWC3P3WFSZ2Y1A", "value": "2086.63", "feed_id": 1738539, "created_at": "2021-11-17T02:23:45.257Z"}, {"id": "0EWEWC2HEW2HS1HSFSQQRV4P0G", "value": "2086.63", "feed_id": 1738539, "created_at": "2021-11-17T04:06:43.913Z"}, {"id": "0EWEY59H0KK18F2ZD16BH9BB9W", "value": "2086.63", "feed_id": 1738539, "created_at": "2021-11-17T05:46:43.688Z"}, {"id": "0EWEZZN5S6JKP83M4CQRYBTTTE", "value": "2086.63", "feed_id": 1738539, "created_at": "2021-11-17T07:28:43.600Z"}, {"id": "0EWF1VQR9K3DDQJ2X913VDHE72", "value": "2086.63", "feed_id": 1738539, "created_at": "2021-11-17T09:13:43.505Z"}, {"id": "0EWF3RCQBVVDBNPHD7AT7VP1SH", "value": "2086.63", "feed_id": 1738539, "created_at": "2021-11-17T10:59:43.679Z"}, {"id": "0EWF5JS54CEVKTJC7R9CX3DD3D", "value": "2086.63", "feed_id": 1738539, "created_at": "2021-11-17T12:41:46.151Z"}, {"id": "0EWF7D41MQK3WFE8GSZ8N4F1VV", "value": "2086.63", "feed_id": 1738539, "created_at": "2021-11-17T14:23:43.579Z"}, {"id": "0EWF96XBWCJJ2H5F5JDX32JNBZ", "value": "2086.63", "feed_id": 1738539, "created_at": "2021-11-17T16:04:43.431Z"}, {"id": "0EWFB193TC7JGKGJMECSW6H5W4", "value": "2086.63", "feed_id": 1738539, "created_at": "2021-11-17T17:46:43.668Z"}, {"id": "0EWFCXBQBFV2VT41KAT3FRVZ9V", "value": "2086.63", "feed_id": 1738539, "created_at": "2021-11-17T19:31:43.678Z"}, {"id": "0EWFEQ5W9CW3N6KVN92CDHG6AQ", "value": "2086.63", "feed_id": 1738539, "created_at": "2021-11-17T21:12:46.263Z"}, {"id": "0EWFGGYDRYPWMVYF70TNRHZK9P", "value": "2086.63", "feed_id": 1738539, "created_at": "2021-11-17T22:53:43.580Z"}, {"id": "0EWFJA6Q9F5JXHD2C5Z8KK6GT8", "value": "2086.63", "feed_id": 1738539, "created_at": "2021-11-18T00:33:47.652Z"}, {"id": "0EWFM3YX5CR2C7DAJHZM4Q0R4P", "value": "2086.63", "feed_id": 1738539, "created_at": "2021-11-18T02:14:43.780Z"}, {"id": "0EWFNXR9JSEAF936GGFPRMCH6K", "value": "2086.63", "feed_id": 1738539, "created_at": "2021-11-18T03:55:43.855Z"}, {"id": "0EWFQQHP436RHNEXCB4GKBY5RS", "value": "2086.63", "feed_id": 1738539, "created_at": "2021-11-18T05:36:43.942Z"}, {"id": "0EWFSHB741Z4ZT45DEQKS84NA8", "value": "2086.63", "feed_id": 1738539, "created_at": "2021-11-18T07:17:44.486Z"}, {"id": "0EWFVC94989MHXHHVN1ERHTPZ7", "value": "2086.63", "feed_id": 1738539, "created_at": "2021-11-18T09:00:44.240Z"}, {"id": "0EWFX6MY38M2K32M9M78WBQWST", "value": "2086.63", "feed_id": 1738539, "created_at": "2021-11-18T10:42:44.669Z"}, {"id": "0EWFYZVWNFRBF9YAXEC2596M76", "value": "2086.63", "feed_id": 1738539, "created_at": "2021-11-18T12:22:44.343Z"}, {"id": "0EWG0T81EWY2XQJRDQ7AMNH7PC", "value": "2086.63", "feed_id": 1738539, "created_at": "2021-11-18T14:04:45.897Z"}, {"id": "0EWG2MVXH942P01MEYW7068HK5", "value": "2086.63", "feed_id": 1738539, "created_at": "2021-11-18T15:47:12.772Z"}, {"id": "0EWG4GC4M204684A8W92MS7ATT", "value": "2086.63", "feed_id": 1738539, "created_at": "2021-11-18T17:31:12.525Z"}, {"id": "0EWG6AMYR28A4ETKGXBAGPDTRD", "value": "2086.63", "feed_id": 1738539, "created_at": "2021-11-18T19:13:03.155Z"}, {"id": "0EWG87A3FZCWC8H8CSE58254C9", "value": "2086.63", "feed_id": 1738539, "created_at": "2021-11-18T20:59:03.910Z"}, {"id": "0EWGA3BSFD1JK4CA1TNGVR61M2", "value": "2086.63", "feed_id": 1738539, "created_at": "2021-11-18T22:44:00.894Z"}, {"id": "0EWGBXQFB2BE56H0537XCXTWGN", "value": "2086.63", "feed_id": 1738539, "created_at": "2021-11-19T00:26:00.918Z"}, {"id": "0EWGDS5YGZ13SVJ9W3G4SKE2EV", "value": "2086.63", "feed_id": 1738539, "created_at": "2021-11-19T02:09:54.947Z"}, {"id": "0EWGFJZ6VSANC8F1XXKE4EJHTJ", "value": "2086.63", "feed_id": 1738539, "created_at": "2021-11-19T03:50:54.604Z"}, {"id": "0EWGHC6AGRGMCW5JWJ40RPN6CE", "value": "2086.63", "feed_id": 1738539, "created_at": "2021-11-19T05:30:54.799Z"}, {"id": "0EWGK6K81RRWMMX7A4348DZYJB", "value": "2086.63", "feed_id": 1738539, "created_at": "2021-11-19T07:12:58.885Z"}, {"id": "0EWGN0BJJJD67M6GGVFYCCHSSX", "value": "2086.63", "feed_id": 1738539, "created_at": "2021-11-19T08:53:55.489Z"}, {"id": "0EWGPSJTHK99704N1356P2JWRF", "value": "2086.63", "feed_id": 1738539, "created_at": "2021-11-19T10:33:56.126Z"}, {"id": "0EWGRKBY61YXF0AA80KQV9DAG6", "value": "2086.63", "feed_id": 1738539, "created_at": "2021-11-19T12:14:55.302Z"}, {"id": "0EWGTCXF868Q1XXPHR2VEREE7P", "value": "2086.63", "feed_id": 1738539, "created_at": "2021-11-19T13:55:29.638Z"}, {"id": "0EWGW7973905PJH51V7Z3XHVG9", "value": "2086.63", "feed_id": 1738539, "created_at": "2021-11-19T15:37:29.866Z"}, {"id": "0EWGY1MX1WABZWET778SVY22B3", "value": "2086.63", "feed_id": 1738539, "created_at": "2021-11-19T17:19:29.900Z"}, {"id": "0EWGZX190CNNYCM6EN74GS441S", "value": "2086.63", "feed_id": 1738539, "created_at": "2021-11-19T19:03:17.044Z"}, {"id": "0EWH1QSQY273SEAAM6H2K84MYP", "value": "2086.63", "feed_id": 1738539, "created_at": "2021-11-19T20:45:58.957Z"}, {"id": "0EWH3J5CR95DWT6JTSEJEBHC3B", "value": "2086.63", "feed_id": 1738539, "created_at": "2021-11-19T22:27:58.874Z"}, {"id": "0EWH5CH4CJVR1DQAB4W55A0EMC", "value": "2086.63", "feed_id": 1738539, "created_at": "2021-11-20T00:09:59.080Z"}, {"id": "0EWH76ER8DMNG8V8AD8DTBVG4W", "value": "2086.63", "feed_id": 1738539, "created_at": "2021-11-20T01:51:13.025Z"}, {"id": "0EWH9088246RCQ8PS6PDTC9FPK", "value": "2086.63", "feed_id": 1738539, "created_at": "2021-11-20T03:32:13.446Z"}, {"id": "0EWHASW9YR4Z89ASB72CS81N0H", "value": "2086.63", "feed_id": 1738539, "created_at": "2021-11-20T05:12:56.059Z"}, {"id": "0EWHCK38K7K48RM7Y7F5RQ7SST", "value": "2086.63", "feed_id": 1738539, "created_at": "2021-11-20T06:52:55.741Z"}, {"id": "0EWHEE77GFHSVMQACB1S05XENY", "value": "2086.63", "feed_id": 1738539, "created_at": "2021-11-20T08:36:15.335Z"}, {"id": "0EWHG8K23TA6S0GY2TM0F88491", "value": "2086.63", "feed_id": 1738539, "created_at": "2021-11-20T10:18:15.845Z"}, {"id": "0EWHJ3H9VKXKX7SFC1NGCHEEV2", "value": "2086.63", "feed_id": 1738539, "created_at": "2021-11-20T12:01:16.683Z"}, {"id": "0EWHKXWJW7EQN67Q3GMKM5C408", "value": "2086.63", "feed_id": 1738539, "created_at": "2021-11-20T13:43:15.392Z"}, {"id": "0EWHNQ3KQ99253GHZGHX38FZ5H", "value": "2086.63", "feed_id": 1738539, "created_at": "2021-11-20T15:23:15.300Z"}, {"id": "0EWHQGWYY37X8YQ9GKY1XP9RPV", "value": "2086.63", "feed_id": 1738539, "created_at": "2021-11-20T17:04:15.251Z"}, {"id": "0EWHSBW471K211F8ME8HBM2PB1", "value": "2086.63", "feed_id": 1738539, "created_at": "2021-11-20T18:47:19.113Z"}, {"id": "0EWHV8FTG0BERMP57E3W9WEFRY", "value": "2086.63", "feed_id": 1738539, "created_at": "2021-11-20T20:33:15.110Z"}, {"id": "0EWHX55XJZ8ATJBTXY11ZZZN81", "value": "2086.63", "feed_id": 1738539, "created_at": "2021-11-20T22:19:18.972Z"}, {"id": "0EWHZ17C3BX19TRQPGNAY74V3A", "value": "2086.63", "feed_id": 1738539, "created_at": "2021-11-21T00:04:15.191Z"}, {"id": "0EWJ0V0T6C5AM5A7B7P99YQ6RM", "value": "2086.63", "feed_id": 1738539, "created_at": "2021-11-21T01:45:15.437Z"}, {"id": "0EWJ2NYQKZPWYN792TDAQVTGNT", "value": "2086.63", "feed_id": 1738539, "created_at": "2021-11-21T03:28:15.219Z"}, {"id": "0EWJ4FRFGCJ07P89VMPAH2GJFJ", "value": "2086.63", "feed_id": 1738539, "created_at": "2021-11-21T05:09:16.468Z"}, {"id": "0EWJ68Z8W9F7GK1TQY3NEYRV6X", "value": "2086.63", "feed_id": 1738539, "created_at": "2021-11-21T06:49:15.610Z"}, {"id": "0EWJ83X20DGMD6M0W459YMMK71", "value": "2086.63", "feed_id": 1738539, "created_at": "2021-11-21T08:32:14.951Z"}, {"id": "0EWJ9ZDHT94W0M70C91A1085V1", "value": "2086.63", "feed_id": 1738539, "created_at": "2021-11-21T10:16:15.597Z"}, {"id": "0EWJBTBVDHWBDZJXE29D9SSWRJ", "value": "2086.63", "feed_id": 1738539, "created_at": "2021-11-21T11:59:16.625Z"}, {"id": "0EWJDPE5QT8QXSAN94SB0S104Q", "value": "2086.63", "feed_id": 1738539, "created_at": "2021-11-21T13:44:15.692Z"}, {"id": "0EWJFGT1G6Z5K2EQZNBZFTAXBX", "value": "0.00", "feed_id": 1738539, "created_at": "2021-11-21T15:26:16.320Z"}, {"id": "0EWJHB5VXZ35GNDYYKGMYFH3BN", "value": "2086.63", "feed_id": 1738539, "created_at": "2021-11-21T17:08:16.812Z"}, {"id": "0EWJK5HHDQDYRAS4KHPM27EZHJ", "value": "2086.63", "feed_id": 1738539, "created_at": "2021-11-21T18:50:16.799Z"}, {"id": "0EWJMZXFFKD9T5Z4RKTAR8H7NQ", "value": "2086.63", "feed_id": 1738539, "created_at": "2021-11-21T20:32:17.662Z"}, {"id": "0EWJPSX60T2GYKAM2MWS45101Z", "value": "2086.63", "feed_id": 1738539, "created_at": "2021-11-21T22:13:38.434Z"}, {"id": "0EWJRNE7MFHF04EPAJ1230JYKF", "value": "2086.63", "feed_id": 1738539, "created_at": "2021-11-21T23:57:40.903Z"}, {"id": "0EWJTFN34F04QEPABQS63RHFGQ", "value": "2086.63", "feed_id": 1738539, "created_at": "2021-11-22T01:39:25.121Z"}, {"id": "0EWJW9EGRC2SQEXB2NH22BMSVF", "value": "2086.63", "feed_id": 1738539, "created_at": "2021-11-22T03:20:25.319Z"}, {"id": "0EWJY2NMM3FT3TTN1CHGEXKW3P", "value": "2086.63", "feed_id": 1738539, "created_at": "2021-11-22T05:00:25.536Z"}, {"id": "0EWJZX165N6P3SXBX2BRJM0ZAX", "value": "2086.63", "feed_id": 1738539, "created_at": "2021-11-22T06:42:25.118Z"}, {"id": "0EWK1QCWDEY0APW38JVHY1HJDR", "value": "2086.63", "feed_id": 1738539, "created_at": "2021-11-22T08:24:25.182Z"}, {"id": "0EWK3HRKTXF184XM2115421XNW", "value": "2086.63", "feed_id": 1738539, "created_at": "2021-11-22T10:06:25.366Z"}, {"id": "0EWK5C4PMW5ZAK4ZDQ8Y6JQT7J", "value": "2086.63", "feed_id": 1738539, "created_at": "2021-11-22T11:48:26.716Z"}, {"id": "0EWK75XMMFQJ3C0VR56BZQ4BT4", "value": "2086.63", "feed_id": 1738539, "created_at": "2021-11-22T13:29:25.313Z"}, {"id": "0EWK8Z63455DGZH0G7ZB0R0G8N", "value": "2086.63", "feed_id": 1738539, "created_at": "2021-11-22T15:09:29.894Z"}, {"id": "0EWKAVFVVQJ7GRRATFZRNV7TZF", "value": "2086.63", "feed_id": 1738539, "created_at": "2021-11-22T16:54:53.375Z"}, {"id": "0EWKCNVRGAD1VS1XC3NGWR884N", "value": "2086.63", "feed_id": 1738539, "created_at": "2021-11-22T18:36:54.093Z"}, {"id": "0EWKEFMXJQ2W1DYJM4VSHWXC53", "value": "2086.63", "feed_id": 1738539, "created_at": "2021-11-22T20:17:53.416Z"}, {"id": "0EWKG938B0A997EE9JC2WN94SM", "value": "2086.63", "feed_id": 1738539, "created_at": "2021-11-22T21:58:17.276Z"}, {"id": "0EWKJ3T0C57D8VW3R70X97BPDW", "value": "2086.63", "feed_id": 1738539, "created_at": "2021-11-22T23:40:53.568Z"}, {"id": "0EWKM2BBPTM3DMA7ZNFX0KB60T", "value": "2086.63", "feed_id": 1738539, "created_at": "2021-11-23T01:30:11.605Z"}, {"id": "0EWKNX9ECHCEHYYXAQ247Y4D20", "value": "2086.63", "feed_id": 1738539, "created_at": "2021-11-23T03:13:11.924Z"}, {"id": "0EWKQRTNRDMWQ92ZYXZ7JR2GDH", "value": "2086.63", "feed_id": 1738539, "created_at": "2021-11-23T04:57:14.983Z"}, {"id": "0EWKSKA8GNNR90QYW0XXXGH0GD", "value": "2086.63", "feed_id": 1738539, "created_at": "2021-11-23T06:39:27.797Z"}, {"id": "0EWKVFCFAD3M3E1KZKNR0M8Z8V", "value": "2086.63", "feed_id": 1738539, "created_at": "2021-11-23T08:24:26.503Z"}, {"id": "0EWKXBMCQ7YR6NYG0K596JS5EQ", "value": "2086.63", "feed_id": 1738539, "created_at": "2021-11-23T10:09:43.907Z"}, {"id": "0EWKZ73XEGBT3PW8QHZ2P4FWES", "value": "2086.63", "feed_id": 1738539, "created_at": "2021-11-23T11:53:41.371Z"}, {"id": "0EWM16PXK3FH9E4P3VEQQTA0MV", "value": "2086.63", "feed_id": 1738539, "created_at": "2021-11-23T13:44:49.673Z"}, {"id": "0EWM32S6D1V9YGZSWCTCKXX9P7", "value": "0.00", "feed_id": 1738539, "created_at": "2021-11-23T15:29:48.585Z"}, {"id": "0EWM4XPZXVJFE9D5J6RD30YH1K", "value": "2086.63", "feed_id": 1738539, "created_at": "2021-11-23T17:12:47.967Z"}, {"id": "0EWM6TRVXMTCKMVH9V3BD6SP7N", "value": "2086.63", "feed_id": 1738539, "created_at": "2021-11-23T18:59:30.424Z"}, {"id": "0EWM8PV2XB4G0C33JZGX4NH2QV", "value": "2086.63", "feed_id": 1738539, "created_at": "2021-11-23T20:44:29.149Z"}, {"id": "0EWMAH6SHVB6TDMPMTRKSBREV5", "value": "2086.63", "feed_id": 1738539, "created_at": "2021-11-23T22:26:29.253Z"}, {"id": "0EWMCC45XZMAZE3PX3ZSYDA3QT", "value": "2086.63", "feed_id": 1738539, "created_at": "2021-11-24T00:09:27.289Z"}, {"id": "0EWME5B7KFBEWQR2BWDG7X7WT3", "value": "2086.63", "feed_id": 1738539, "created_at": "2021-11-24T01:49:27.281Z"}, {"id": "0EWMFZ5057301CD1PYTQ89T13H", "value": "2086.63", "feed_id": 1738539, "created_at": "2021-11-24T03:30:28.599Z"}, {"id": "0EWMHRY0K6XACT58VE14YQF12N", "value": "2086.63", "feed_id": 1738539, "created_at": "2021-11-24T05:11:27.447Z"}, {"id": "0EWMKMEA0Y5APGV3EHMPB182AF", "value": "2086.63", "feed_id": 1738539, "created_at": "2021-11-24T06:55:27.439Z"}, {"id": "0EWMNDNMM9AT0E9DGJC05A410D", "value": "2086.63", "feed_id": 1738539, "created_at": "2021-11-24T08:35:28.346Z"}]